fulladder.v
module full_adder(a,b,cin,sum,cout);
input a ,b,cin;
output sum, cout;
assign sum=(a^b^cin);
assign cout=(a&b)|(b&cin)|(cin&a);
endmodule

test_adder.v
module full_adder_test;
  reg a,b,cin;
  wire sum,cout;
 
// instantiate the DUT block  
  full_adder f1(.a(a),.b(b),.cin(cin),.sum(sum),.cout(cout));
 
// this particular line is added to dump the file on online simulator
  initial 
   begin 
    $dumpfile("full_tb.vcd");
    $dumpvars(); 
   end

// insert all the inputs 
  initial begin a=1'b1;  #4; a=1'b0;#10 $stop();end
  initial begin b=1'b1; forever #2 b=~b;end
  initial begin cin=1'b1;forever #1 cin=~cin; #10 $stop();end



 initial 
  begin 
   $monitor(" time=%0d A=%b B=%b Cin=%b Sum=%b Cout=%b",   $time,a,b,cin,sum,cout);
  end
 endmodule

full_tb.vcd
$date
	Sun Aug 27 16:16:48 2023
$end
$version
	Icarus Verilog
$end
$timescale
	1s
$end
$scope module full_adder_test $end
$var wire 1 ! sum $end
$var wire 1 " cout $end
$var reg 1 # a $end
$var reg 1 $ b $end
$var reg 1 % cin $end
$scope module f1 $end
$var wire 1 # a $end
$var wire 1 $ b $end
$var wire 1 % cin $end
$var wire 1 " cout $end
$var wire 1 ! sum $end
$upscope $end
$upscope $end
$enddefinitions $end
#0
$dumpvars
1%
1$
1#
1"
1!
$end
#1
0!
0%
#2
1%
0$
#3
0"
1!
0%
#4
1"
0!
1%
1$
0#
#5
0"
1!
0%
#6
1%
0$
#7
0!
0%
#8
1"
1%
1$
#9
0"
1!
0%
#10
1%
0$
#11
0!
0%
#12
1"
1%
1$
#13
0"
1!
0%
